{"assets":{"1A48C065E04CB006F5CC406BA66265A3":{"type":"texture","index":3,"assetRequest":{"type":"slide","state":"contents","slide":"none"},"url":{"native":"assets\/25F66D9A-C20D-4B69-B1EB-9A315715858A.pdf"},"width":512,"height":790},"91995A66483849D7F9A9124E526CBC07":{"type":"texture","index":6,"assetRequest":{"type":"slide","state":"contents","slide":"none"},"url":{"native":"assets\/25F66D9A-C20D-4B69-B1EB-9A315715858A.pdf"},"width":1024,"height":768},"9F584237C7180F7CC6232FB7C47C8A47":{"type":"texture","index":4,"assetRequest":{"type":"slide","state":"contents","slide":"none"},"url":{"native":"assets\/25F66D9A-C20D-4B69-B1EB-9A315715858A.pdf"},"width":512,"height":35},"2F1EFC68E984CE802436156E23DAACE1":{"type":"texture","index":7,"assetRequest":{"type":"slide","state":"contents","slide":"none"},"url":{"native":"assets\/25F66D9A-C20D-4B69-B1EB-9A315715858A.pdf"},"width":1024,"height":768},"C725CB90B3A1E5FF17DB9DDA74434158":{"type":"texture","index":5,"assetRequest":{"type":"slide","state":"contents","slide":"none"},"url":{"native":"assets\/25F66D9A-C20D-4B69-B1EB-9A315715858A.pdf"},"width":1024,"height":768},"6DFA3B9F9D9C6EEBCCE61DD0C56C0D32":{"type":"texture","index":1,"assetRequest":{"type":"slide","state":"contents","slide":"none"},"url":{"native":"assets\/25F66D9A-C20D-4B69-B1EB-9A315715858A.pdf"},"width":383,"height":137},"2298F96260E9A7107DD42A18E70624F1":{"type":"texture","index":2,"assetRequest":{"type":"slide","state":"contents","slide":"none"},"url":{"native":"assets\/25F66D9A-C20D-4B69-B1EB-9A315715858A.pdf"},"width":624,"height":462},"DB8451458D98EFA7506DBEBC2B1323F0":{"type":"texture","index":0,"assetRequest":{"type":"slide","state":"contents","slide":"none"},"url":{"native":"assets\/25F66D9A-C20D-4B69-B1EB-9A315715858A.pdf"},"width":1024,"height":768}},"events":[{"effects":[{"beginTime":0,"baseLayer":{"animations":[],"initialState":{"affineTransform":[1,0,0,1,0,0],"masksToBounds":false,"rotation":0,"scale":1,"position":{"pointX":768,"pointY":395},"width":512,"sublayerTransform":[1,0,0,0,0,1,0,0,0,0,1,0,0,0,0,1],"contentsRect":{"y":0,"x":0,"width":1,"height":1},"opacity":1,"edgeAntialiasingMask":251658240,"height":790,"hidden":false,"anchorPoint":{"pointX":0.5,"pointY":0.5}},"objectID":"492D8BB6-D6CD-4652-8BE1-F3A0B8A19036","layers":[{"animations":[],"layers":[],"texturedRectangle":{"isBackgroundTexture":false,"singleTextureOpacity":1,"textureType":5,"textBaseline":0,"textXHeight":0,"isVerticalText":false},"initialState":{"affineTransform":[1,0,0,1,0,0],"masksToBounds":false,"rotation":0,"scale":1,"position":{"pointX":256,"pointY":395},"width":512,"sublayerTransform":[1,0,0,0,0,1,0,0,0,0,1,0,0,0,0,1],"contentsRect":{"y":0,"x":0,"width":1,"height":1},"opacity":1,"edgeAntialiasingMask":0,"height":790,"hidden":false,"anchorPoint":{"pointX":0.5,"pointY":0.5}},"texture":"1A48C065E04CB006F5CC406BA66265A3"},{"animations":[],"layers":[],"texturedRectangle":{"isBackgroundTexture":false,"singleTextureOpacity":1,"textureType":6,"textBaseline":0,"textXHeight":0,"isVerticalText":false},"initialState":{"affineTransform":[1,0,0,1,0,0],"masksToBounds":false,"rotation":0,"scale":1,"position":{"pointX":256,"pointY":752.5},"width":512,"sublayerTransform":[1,0,0,0,0,1,0,0,0,0,1,0,0,0,0,1],"contentsRect":{"y":0,"x":0,"width":1,"height":1},"opacity":1,"edgeAntialiasingMask":0,"height":35,"hidden":false,"anchorPoint":{"pointX":0.5,"pointY":0.5}},"texture":"9F584237C7180F7CC6232FB7C47C8A47"}]},"effects":[],"duration":0.5,"type":"smartBuild","name":"apple:gallery-appear","objectID":"492D8BB6-D6CD-4652-8BE1-F3A0B8A19036"}],"automaticPlay":false,"hyperlinks":[{"url":"?slideid=7A8F8EC3-1350-4772-B2DD-69E807327D19","events":{"7A8F8EC3-1350-4772-B2DD-69E807327D19":{"effects":[{"beginTime":0,"baseLayer":{"animations":[],"initialState":{"affineTransform":[1,0,0,1,0,0],"masksToBounds":false,"rotation":0,"scale":1,"position":{"pointX":512,"pointY":384},"width":1024,"sublayerTransform":[1,0,0,0,0,1,0,0,0,0,1,0,0,0,0,1],"contentsRect":{"y":0,"x":0,"width":1,"height":1},"opacity":1,"edgeAntialiasingMask":251658240,"height":768,"hidden":false,"anchorPoint":{"pointX":0.5,"pointY":0.5}},"objectID":"0","layers":[{"animations":[],"initialState":{"affineTransform":[1,0,0,1,0,0],"masksToBounds":false,"rotation":0,"scale":1,"position":{"pointX":512,"pointY":384},"width":1024,"sublayerTransform":[1,0,0,0,0,1,0,0,0,0,1,-0.00049229876906403734,0,0,0,1],"contentsRect":{"y":0,"x":0,"width":1,"height":1},"opacity":1,"edgeAntialiasingMask":251658240,"height":768,"hidden":false,"anchorPoint":{"pointX":0.5,"pointY":0.5}},"layers":[{"animations":[],"layers":[],"texturedRectangle":{"isBackgroundTexture":false,"singleTextureOpacity":1,"textureType":0,"textBaseline":0,"textXHeight":0,"isVerticalText":false},"initialState":{"affineTransform":[1,0,0,1,0,0],"masksToBounds":false,"rotation":0,"scale":1,"position":{"pointX":512,"pointY":384},"width":1024,"sublayerTransform":[1,0,0,0,0,1,0,0,0,0,1,0,0,0,0,1],"contentsRect":{"y":0,"x":0,"width":1,"height":1},"opacity":1,"edgeAntialiasingMask":0,"height":768,"hidden":false,"anchorPoint":{"pointX":0.5,"pointY":0.5}},"texture":"91995A66483849D7F9A9124E526CBC07"},{"animations":[{"timeOffset":0,"from":{"scalar":false},"beginTime":0,"repeatCount":0,"fillMode":"both","property":"hidden","autoreverses":false,"duration":0.01,"to":{"scalar":true}}],"layers":[],"texturedRectangle":{"isBackgroundTexture":false,"singleTextureOpacity":1,"textureType":0,"textBaseline":0,"textXHeight":0,"isVerticalText":false},"initialState":{"affineTransform":[1,0,0,1,0,0],"masksToBounds":false,"rotation":0,"scale":1,"position":{"pointX":512,"pointY":384},"width":1024,"sublayerTransform":[1,0,0,0,0,1,0,0,0,0,1,0,0,0,0,1],"contentsRect":{"y":0,"x":0,"width":1,"height":1},"opacity":1,"edgeAntialiasingMask":0,"height":768,"hidden":false,"anchorPoint":{"pointX":0.5,"pointY":0.5}},"texture":"C725CB90B3A1E5FF17DB9DDA74434158"}]}]},"effects":[],"duration":0.01,"type":"transition","name":"none","objectID":"0"}],"automaticPlay":false,"hyperlinks":[],"accessibility":[],"baseLayer":{"animations":[],"initialState":{"affineTransform":[1,0,0,1,0,0],"masksToBounds":false,"rotation":0,"scale":1,"position":{"pointX":512,"pointY":384},"width":1024,"sublayerTransform":[1,0,0,0,0,1,0,0,0,0,1,0,0,0,0,1],"contentsRect":{"y":0,"x":0,"width":1,"height":1},"opacity":1,"edgeAntialiasingMask":251658240,"height":768,"hidden":false,"anchorPoint":{"pointX":0.5,"pointY":0.5}},"objectID":"0","layers":[{"animations":[],"initialState":{"affineTransform":[1,0,0,1,0,0],"masksToBounds":false,"rotation":0,"scale":1,"position":{"pointX":512,"pointY":384},"width":1024,"sublayerTransform":[1,0,0,0,0,1,0,0,0,0,1,-0.00049229876906403734,0,0,0,1],"contentsRect":{"y":0,"x":0,"width":1,"height":1},"opacity":1,"edgeAntialiasingMask":251658240,"height":768,"hidden":false,"anchorPoint":{"pointX":0.5,"pointY":0.5}},"layers":[{"animations":[],"layers":[],"texturedRectangle":{"isBackgroundTexture":false,"singleTextureOpacity":1,"textureType":0,"textBaseline":0,"textXHeight":0,"isVerticalText":false},"initialState":{"affineTransform":[1,0,0,1,0,0],"masksToBounds":false,"rotation":0,"scale":1,"position":{"pointX":512,"pointY":384},"width":1024,"sublayerTransform":[1,0,0,0,0,1,0,0,0,0,1,0,0,0,0,1],"contentsRect":{"y":0,"x":0,"width":1,"height":1},"opacity":1,"edgeAntialiasingMask":0,"height":768,"hidden":false,"anchorPoint":{"pointX":0.5,"pointY":0.5}},"texture":"C725CB90B3A1E5FF17DB9DDA74434158"}]}]}}},"targetRectangle":{"y":52,"x":56,"width":379.61999831020836,"height":31}},{"url":"https:\/\/www.youtube.com\/watch?v=jDyxxZBbeeg","targetRectangle":{"y":175,"x":56,"width":70.547999699592594,"height":14}},{"url":"https:\/\/en.wikipedia.org\/wiki\/Rite_of_Spring_(film)","targetRectangle":{"y":230,"x":111.49000003496803,"width":214.31910000000005,"height":27}},{"url":"https:\/\/en.wikipedia.org\/wiki\/Benilde_or_the_Virgin_Mother#:~:text=Benilde%20or%20the%20Virgin%20Mother%20(Benilde%20ou%20a%20Virgem%20M%C3%A3e,directed%20by%20Manoel%20de%20Oliveira.","targetRectangle":{"y":302,"x":111.49000003496803,"width":288.19200000000001,"height":52.280000686645508}},{"url":"https:\/\/www.youtube.com\/watch?v=jZ2SbJO6zF8","targetRectangle":{"y":354.28000068664551,"x":111.49000003496803,"width":261.00809999999996,"height":54}},{"url":"https:\/\/www.youtube.com\/watch?v=KEuUJtXJH0U","targetRectangle":{"y":426.28000068664551,"x":122.27350003496804,"width":111.62699999999998,"height":52.280000686645508}},{"url":"https:\/\/en.wikipedia.org\/wiki\/Abraham's_Valley","targetRectangle":{"y":496.56000137329102,"x":111.49000003496803,"width":137.00969999999998,"height":52.280000686645508}},{"url":"https:\/\/www.youtube.com\/watch?v=d8nA0H44npA","targetRectangle":{"y":548.84000205993652,"x":122.27350003496804,"width":200.45459999999997,"height":27}},{"url":"https:\/\/en.wikipedia.org\/wiki\/The_Convent_(1995_film)","targetRectangle":{"y":593.84000205993652,"x":111.49000003496803,"width":128.52510000000001,"height":52.280000686645508}},{"url":"https:\/\/www.youtube.com\/watch?v=z9HYOHZ4ORk","targetRectangle":{"y":646.12000274658203,"x":122.27350003496804,"width":142.7688,"height":27}},{"url":"https:\/\/en.wikipedia.org\/wiki\/Manoel_de_Oliveira","targetRectangle":{"y":0,"x":512,"width":512,"height":790}}],"accessibility":[{"text":"Manoel de oliveira","targetRectangle":{"y":52,"x":56,"width":379.61999831020836,"height":31}},{"text":"(1908-2015)","targetRectangle":{"y":128,"x":56,"width":130.55279936914445,"height":19}},{"text":"Profile","targetRectangle":{"y":175,"x":56,"width":70.547999699592594,"height":14}},{"text":"Acto Da Primavera                                                                  (Rite Of Spring)                                       (1963)","targetRectangle":{"y":230,"x":111.49000003496803,"width":605.36909999999989,"height":72}},{"text":"Benilde Ou A Virgem Mãe                          (Benilde Or The Virgin Mother)                                           (1975)","targetRectangle":{"y":302,"x":111.49000003496803,"width":442.24199999999996,"height":124.28000068664551}},{"text":"(Francisca)                                                                         (1981)","targetRectangle":{"y":426.28000068664551,"x":111.49000003496803,"width":565.71900000000051,"height":70.280000686645508}},{"text":"Vale Abraão                                                               (Abraham’s Valley)                              (1993)","targetRectangle":{"y":496.56000137329102,"x":111.49000003496803,"width":510.28469999999993,"height":97.280000686645508}},{"text":"O Convento                                                (The Convent)                                             (1995)","targetRectangle":{"y":593.84000205993652,"x":111.49000003496803,"width":430.96080000000029,"height":97.280000686645508}},{"text":"Portugal","targetRectangle":{"y":741,"x":726.96000000000004,"width":82.079999999999927,"height":23}}],"baseLayer":{"animations":[],"initialState":{"affineTransform":[1,0,0,1,0,0],"masksToBounds":false,"rotation":0,"scale":1,"position":{"pointX":512,"pointY":384},"width":1024,"sublayerTransform":[1,0,0,0,0,1,0,0,0,0,1,0,0,0,0,1],"contentsRect":{"y":0,"x":0,"width":1,"height":1},"opacity":1,"edgeAntialiasingMask":251658240,"height":768,"hidden":false,"anchorPoint":{"pointX":0.5,"pointY":0.5}},"layers":[{"animations":[],"initialState":{"affineTransform":[1,0,0,1,0,0],"masksToBounds":false,"rotation":0,"scale":1,"position":{"pointX":512,"pointY":384},"width":1024,"sublayerTransform":[1,0,0,0,0,1,0,0,0,0,1,0,0,0,0,1],"contentsRect":{"y":0,"x":0,"width":1,"height":1},"opacity":1,"edgeAntialiasingMask":251658240,"height":768,"hidden":false,"anchorPoint":{"pointX":0.5,"pointY":0.5}},"layers":[{"animations":[],"initialState":{"affineTransform":[1,0,0,1,0,0],"masksToBounds":false,"rotation":0,"scale":1,"position":{"pointX":512,"pointY":384},"width":1024,"sublayerTransform":[1,0,0,0,0,1,0,0,0,0,1,0,0,0,0,1],"contentsRect":{"y":0,"x":0,"width":1,"height":1},"opacity":1,"edgeAntialiasingMask":251658240,"height":768,"hidden":false,"anchorPoint":{"pointX":0.5,"pointY":0.5}},"layers":[{"animations":[],"layers":[],"texturedRectangle":{"isBackgroundTexture":true,"singleTextureOpacity":1,"textureType":1,"textBaseline":0,"textXHeight":0,"isVerticalText":false},"initialState":{"affineTransform":[1,0,0,1,0,0],"masksToBounds":false,"rotation":0,"scale":1,"position":{"pointX":512,"pointY":384},"width":1024,"sublayerTransform":[1,0,0,0,0,1,0,0,0,0,1,0,0,0,0,1],"contentsRect":{"y":0,"x":0,"width":1,"height":1},"opacity":1,"edgeAntialiasingMask":0,"height":768,"hidden":false,"anchorPoint":{"pointX":0.5,"pointY":0.5}},"texture":"DB8451458D98EFA7506DBEBC2B1323F0"}]}]},{"animations":[],"initialState":{"affineTransform":[1,0,0,1,0,0],"masksToBounds":false,"rotation":0,"scale":1,"position":{"pointX":512,"pointY":384},"width":1024,"sublayerTransform":[1,0,0,0,0,1,0,0,0,0,1,0,0,0,0,1],"contentsRect":{"y":0,"x":0,"width":1,"height":1},"opacity":1,"edgeAntialiasingMask":251658240,"height":768,"hidden":false,"anchorPoint":{"pointX":0.5,"pointY":0.5}},"layers":[{"animations":[],"initialState":{"affineTransform":[1,0,0,1,0,0],"masksToBounds":false,"rotation":0,"scale":1,"position":{"pointX":243.5,"pointY":116.5},"width":383,"sublayerTransform":[1,0,0,0,0,1,0,0,0,0,1,0,0,0,0,1],"contentsRect":{"y":0,"x":0,"width":1,"height":1},"opacity":1,"edgeAntialiasingMask":251658240,"height":137,"hidden":false,"anchorPoint":{"pointX":0.5,"pointY":0.5}},"layers":[{"animations":[],"layers":[],"texturedRectangle":{"singleTextureOpacity":1,"textXHeight":0.098737226277372261,"textBaseline":0.97564964572878654,"isBackgroundTexture":true,"isVerticalText":false,"textColor":[0.9999966025352478,0.99999994039535522,0.99999994039535522,1],"textureType":6},"initialState":{"affineTransform":[1,0,0,1,0,0],"masksToBounds":false,"rotation":0,"scale":1,"position":{"pointX":194.5,"pointY":72.5},"width":383,"sublayerTransform":[1,0,0,0,0,1,0,0,0,0,1,0,0,0,0,1],"contentsRect":{"y":0,"x":0,"width":1,"height":1},"opacity":1,"edgeAntialiasingMask":0,"height":137,"hidden":false,"anchorPoint":{"pointX":0.5,"pointY":0.5}},"texture":"6DFA3B9F9D9C6EEBCCE61DD0C56C0D32"}]}]},{"animations":[],"initialState":{"affineTransform":[1,0,0,1,0,0],"masksToBounds":false,"rotation":0,"scale":1,"position":{"pointX":512,"pointY":384},"width":1024,"sublayerTransform":[1,0,0,0,0,1,0,0,0,0,1,0,0,0,0,1],"contentsRect":{"y":0,"x":0,"width":1,"height":1},"opacity":1,"edgeAntialiasingMask":251658240,"height":768,"hidden":false,"anchorPoint":{"pointX":0.5,"pointY":0.5}},"layers":[{"animations":[],"initialState":{"affineTransform":[1,0,0,1,0,0],"masksToBounds":false,"rotation":0,"scale":1,"position":{"pointX":364,"pointY":453},"width":624,"sublayerTransform":[1,0,0,0,0,1,0,0,0,0,1,0,0,0,0,1],"contentsRect":{"y":0,"x":0,"width":1,"height":1},"opacity":1,"edgeAntialiasingMask":251658240,"height":462,"hidden":false,"anchorPoint":{"pointX":0.5,"pointY":0.5}},"layers":[{"animations":[],"layers":[],"texturedRectangle":{"singleTextureOpacity":1,"textXHeight":0.025700649350649349,"textBaseline":0.98954546049043735,"isBackgroundTexture":true,"isVerticalText":false,"textColor":[0.9999966025352478,0.99999994039535522,0.99999994039535522,1],"textureType":6},"initialState":{"affineTransform":[1,0,0,1,0,0],"masksToBounds":false,"rotation":0,"scale":1,"position":{"pointX":347,"pointY":239},"width":624,"sublayerTransform":[1,0,0,0,0,1,0,0,0,0,1,0,0,0,0,1],"contentsRect":{"y":0,"x":0,"width":1,"height":1},"opacity":1,"edgeAntialiasingMask":0,"height":462,"hidden":false,"anchorPoint":{"pointX":0.5,"pointY":0.5}},"texture":"2298F96260E9A7107DD42A18E70624F1"}]}]},{"animations":[],"initialState":{"affineTransform":[1,0,0,1,0,0],"masksToBounds":false,"rotation":0,"scale":1,"position":{"pointX":512,"pointY":384},"width":1024,"sublayerTransform":[1,0,0,0,0,1,0,0,0,0,1,0,0,0,0,1],"contentsRect":{"y":0,"x":0,"width":1,"height":1},"opacity":1,"edgeAntialiasingMask":251658240,"height":768,"hidden":false,"anchorPoint":{"pointX":0.5,"pointY":0.5}},"layers":[{"animations":[],"initialState":{"affineTransform":[1,0,0,1,0,0],"masksToBounds":false,"rotation":0,"scale":1,"position":{"pointX":768,"pointY":395},"width":512,"sublayerTransform":[1,0,0,0,0,1,0,0,0,0,1,0,0,0,0,1],"contentsRect":{"y":0,"x":0,"width":1,"height":1},"opacity":1,"edgeAntialiasingMask":251658240,"height":790,"hidden":false,"anchorPoint":{"pointX":0.5,"pointY":0.5}},"objectID":"492D8BB6-D6CD-4652-8BE1-F3A0B8A19036","layers":[{"animations":[],"layers":[],"texturedRectangle":{"isBackgroundTexture":false,"singleTextureOpacity":1,"textureType":5,"textBaseline":0,"textXHeight":0,"isVerticalText":false},"initialState":{"affineTransform":[1,0,0,1,0,0],"masksToBounds":false,"rotation":0,"scale":1,"position":{"pointX":256,"pointY":395},"width":512,"sublayerTransform":[1,0,0,0,0,1,0,0,0,0,1,0,0,0,0,1],"contentsRect":{"y":0,"x":0,"width":1,"height":1},"opacity":1,"edgeAntialiasingMask":0,"height":790,"hidden":false,"anchorPoint":{"pointX":0.5,"pointY":0.5}},"texture":"1A48C065E04CB006F5CC406BA66265A3"},{"animations":[],"layers":[],"texturedRectangle":{"isBackgroundTexture":false,"singleTextureOpacity":1,"textureType":6,"textBaseline":0,"textXHeight":0,"isVerticalText":false},"initialState":{"affineTransform":[1,0,0,1,0,0],"masksToBounds":false,"rotation":0,"scale":1,"position":{"pointX":256,"pointY":752.5},"width":512,"sublayerTransform":[1,0,0,0,0,1,0,0,0,0,1,0,0,0,0,1],"contentsRect":{"y":0,"x":0,"width":1,"height":1},"opacity":1,"edgeAntialiasingMask":0,"height":35,"hidden":false,"anchorPoint":{"pointX":0.5,"pointY":0.5}},"texture":"9F584237C7180F7CC6232FB7C47C8A47"}]}]}]}},{"effects":[{"beginTime":0,"baseLayer":{"animations":[],"initialState":{"affineTransform":[1,0,0,1,0,0],"masksToBounds":false,"rotation":0,"scale":1,"position":{"pointX":512,"pointY":384},"width":1024,"sublayerTransform":[1,0,0,0,0,1,0,0,0,0,1,0,0,0,0,1],"contentsRect":{"y":0,"x":0,"width":1,"height":1},"opacity":1,"edgeAntialiasingMask":251658240,"height":768,"hidden":false,"anchorPoint":{"pointX":0.5,"pointY":0.5}},"objectID":"0","layers":[{"animations":[],"initialState":{"affineTransform":[1,0,0,1,0,0],"masksToBounds":false,"rotation":0,"scale":1,"position":{"pointX":512,"pointY":384},"width":1024,"sublayerTransform":[1,0,0,0,0,1,0,0,0,0,1,-0.00049229876906403734,0,0,0,1],"contentsRect":{"y":0,"x":0,"width":1,"height":1},"opacity":1,"edgeAntialiasingMask":251658240,"height":768,"hidden":false,"anchorPoint":{"pointX":0.5,"pointY":0.5}},"layers":[{"animations":[],"layers":[],"texturedRectangle":{"isBackgroundTexture":false,"singleTextureOpacity":1,"textureType":0,"textBaseline":0,"textXHeight":0,"isVerticalText":false},"initialState":{"affineTransform":[1,0,0,1,0,0],"masksToBounds":false,"rotation":0,"scale":1,"position":{"pointX":512,"pointY":384},"width":1024,"sublayerTransform":[1,0,0,0,0,1,0,0,0,0,1,0,0,0,0,1],"contentsRect":{"y":0,"x":0,"width":1,"height":1},"opacity":1,"edgeAntialiasingMask":0,"height":768,"hidden":false,"anchorPoint":{"pointX":0.5,"pointY":0.5}},"texture":"2F1EFC68E984CE802436156E23DAACE1"},{"animations":[{"timeOffset":0,"from":{"scalar":false},"beginTime":0,"repeatCount":0,"fillMode":"both","property":"hidden","autoreverses":false,"duration":0.01,"to":{"scalar":true}}],"layers":[],"texturedRectangle":{"isBackgroundTexture":false,"singleTextureOpacity":1,"textureType":0,"textBaseline":0,"textXHeight":0,"isVerticalText":false},"initialState":{"affineTransform":[1,0,0,1,0,0],"masksToBounds":false,"rotation":0,"scale":1,"position":{"pointX":512,"pointY":384},"width":1024,"sublayerTransform":[1,0,0,0,0,1,0,0,0,0,1,0,0,0,0,1],"contentsRect":{"y":0,"x":0,"width":1,"height":1},"opacity":1,"edgeAntialiasingMask":0,"height":768,"hidden":false,"anchorPoint":{"pointX":0.5,"pointY":0.5}},"texture":"C725CB90B3A1E5FF17DB9DDA74434158"}]}]},"effects":[],"duration":0.01,"type":"transition","name":"none","objectID":"0"}],"automaticPlay":false,"hyperlinks":[{"url":"?slideid=7A8F8EC3-1350-4772-B2DD-69E807327D19","events":{"7A8F8EC3-1350-4772-B2DD-69E807327D19":{"effects":[{"beginTime":0,"baseLayer":{"animations":[],"initialState":{"affineTransform":[1,0,0,1,0,0],"masksToBounds":false,"rotation":0,"scale":1,"position":{"pointX":512,"pointY":384},"width":1024,"sublayerTransform":[1,0,0,0,0,1,0,0,0,0,1,0,0,0,0,1],"contentsRect":{"y":0,"x":0,"width":1,"height":1},"opacity":1,"edgeAntialiasingMask":251658240,"height":768,"hidden":false,"anchorPoint":{"pointX":0.5,"pointY":0.5}},"objectID":"0","layers":[{"animations":[],"initialState":{"affineTransform":[1,0,0,1,0,0],"masksToBounds":false,"rotation":0,"scale":1,"position":{"pointX":512,"pointY":384},"width":1024,"sublayerTransform":[1,0,0,0,0,1,0,0,0,0,1,-0.00049229876906403734,0,0,0,1],"contentsRect":{"y":0,"x":0,"width":1,"height":1},"opacity":1,"edgeAntialiasingMask":251658240,"height":768,"hidden":false,"anchorPoint":{"pointX":0.5,"pointY":0.5}},"layers":[{"animations":[],"layers":[],"texturedRectangle":{"isBackgroundTexture":false,"singleTextureOpacity":1,"textureType":0,"textBaseline":0,"textXHeight":0,"isVerticalText":false},"initialState":{"affineTransform":[1,0,0,1,0,0],"masksToBounds":false,"rotation":0,"scale":1,"position":{"pointX":512,"pointY":384},"width":1024,"sublayerTransform":[1,0,0,0,0,1,0,0,0,0,1,0,0,0,0,1],"contentsRect":{"y":0,"x":0,"width":1,"height":1},"opacity":1,"edgeAntialiasingMask":0,"height":768,"hidden":false,"anchorPoint":{"pointX":0.5,"pointY":0.5}},"texture":"91995A66483849D7F9A9124E526CBC07"},{"animations":[{"timeOffset":0,"from":{"scalar":false},"beginTime":0,"repeatCount":0,"fillMode":"both","property":"hidden","autoreverses":false,"duration":0.01,"to":{"scalar":true}}],"layers":[],"texturedRectangle":{"isBackgroundTexture":false,"singleTextureOpacity":1,"textureType":0,"textBaseline":0,"textXHeight":0,"isVerticalText":false},"initialState":{"affineTransform":[1,0,0,1,0,0],"masksToBounds":false,"rotation":0,"scale":1,"position":{"pointX":512,"pointY":384},"width":1024,"sublayerTransform":[1,0,0,0,0,1,0,0,0,0,1,0,0,0,0,1],"contentsRect":{"y":0,"x":0,"width":1,"height":1},"opacity":1,"edgeAntialiasingMask":0,"height":768,"hidden":false,"anchorPoint":{"pointX":0.5,"pointY":0.5}},"texture":"C725CB90B3A1E5FF17DB9DDA74434158"}]}]},"effects":[],"duration":0.01,"type":"transition","name":"none","objectID":"0"}],"automaticPlay":false,"hyperlinks":[],"accessibility":[],"baseLayer":{"animations":[],"initialState":{"affineTransform":[1,0,0,1,0,0],"masksToBounds":false,"rotation":0,"scale":1,"position":{"pointX":512,"pointY":384},"width":1024,"sublayerTransform":[1,0,0,0,0,1,0,0,0,0,1,0,0,0,0,1],"contentsRect":{"y":0,"x":0,"width":1,"height":1},"opacity":1,"edgeAntialiasingMask":251658240,"height":768,"hidden":false,"anchorPoint":{"pointX":0.5,"pointY":0.5}},"objectID":"0","layers":[{"animations":[],"initialState":{"affineTransform":[1,0,0,1,0,0],"masksToBounds":false,"rotation":0,"scale":1,"position":{"pointX":512,"pointY":384},"width":1024,"sublayerTransform":[1,0,0,0,0,1,0,0,0,0,1,-0.00049229876906403734,0,0,0,1],"contentsRect":{"y":0,"x":0,"width":1,"height":1},"opacity":1,"edgeAntialiasingMask":251658240,"height":768,"hidden":false,"anchorPoint":{"pointX":0.5,"pointY":0.5}},"layers":[{"animations":[],"layers":[],"texturedRectangle":{"isBackgroundTexture":false,"singleTextureOpacity":1,"textureType":0,"textBaseline":0,"textXHeight":0,"isVerticalText":false},"initialState":{"affineTransform":[1,0,0,1,0,0],"masksToBounds":false,"rotation":0,"scale":1,"position":{"pointX":512,"pointY":384},"width":1024,"sublayerTransform":[1,0,0,0,0,1,0,0,0,0,1,0,0,0,0,1],"contentsRect":{"y":0,"x":0,"width":1,"height":1},"opacity":1,"edgeAntialiasingMask":0,"height":768,"hidden":false,"anchorPoint":{"pointX":0.5,"pointY":0.5}},"texture":"C725CB90B3A1E5FF17DB9DDA74434158"}]}]}}},"targetRectangle":{"y":52,"x":56,"width":379.61999831020836,"height":31}},{"url":"https:\/\/www.youtube.com\/watch?v=jDyxxZBbeeg","targetRectangle":{"y":175,"x":56,"width":70.547999699592594,"height":14}},{"url":"https:\/\/en.wikipedia.org\/wiki\/Rite_of_Spring_(film)","targetRectangle":{"y":230,"x":111.49000003496803,"width":214.31910000000005,"height":27}},{"url":"https:\/\/en.wikipedia.org\/wiki\/Benilde_or_the_Virgin_Mother#:~:text=Benilde%20or%20the%20Virgin%20Mother%20(Benilde%20ou%20a%20Virgem%20M%C3%A3e,directed%20by%20Manoel%20de%20Oliveira.","targetRectangle":{"y":302,"x":111.49000003496803,"width":288.19200000000001,"height":52.280000686645508}},{"url":"https:\/\/www.youtube.com\/watch?v=jZ2SbJO6zF8","targetRectangle":{"y":354.28000068664551,"x":111.49000003496803,"width":261.00809999999996,"height":54}},{"url":"https:\/\/www.youtube.com\/watch?v=KEuUJtXJH0U","targetRectangle":{"y":426.28000068664551,"x":122.27350003496804,"width":111.62699999999998,"height":52.280000686645508}},{"url":"https:\/\/en.wikipedia.org\/wiki\/Abraham's_Valley","targetRectangle":{"y":496.56000137329102,"x":111.49000003496803,"width":137.00969999999998,"height":52.280000686645508}},{"url":"https:\/\/www.youtube.com\/watch?v=d8nA0H44npA","targetRectangle":{"y":548.84000205993652,"x":122.27350003496804,"width":200.45459999999997,"height":27}},{"url":"https:\/\/en.wikipedia.org\/wiki\/The_Convent_(1995_film)","targetRectangle":{"y":593.84000205993652,"x":111.49000003496803,"width":128.52510000000001,"height":52.280000686645508}},{"url":"https:\/\/www.youtube.com\/watch?v=z9HYOHZ4ORk","targetRectangle":{"y":646.12000274658203,"x":122.27350003496804,"width":142.7688,"height":27}},{"url":"https:\/\/en.wikipedia.org\/wiki\/Manoel_de_Oliveira","targetRectangle":{"y":0,"x":512,"width":512,"height":790}}],"accessibility":[{"text":"Manoel de oliveira","targetRectangle":{"y":52,"x":56,"width":379.61999831020836,"height":31}},{"text":"(1908-2015)","targetRectangle":{"y":128,"x":56,"width":130.55279936914445,"height":19}},{"text":"Profile","targetRectangle":{"y":175,"x":56,"width":70.547999699592594,"height":14}},{"text":"Acto Da Primavera                                                                  (Rite Of Spring)                                       (1963)","targetRectangle":{"y":230,"x":111.49000003496803,"width":605.36909999999989,"height":72}},{"text":"Benilde Ou A Virgem Mãe                          (Benilde Or The Virgin Mother)                                           (1975)","targetRectangle":{"y":302,"x":111.49000003496803,"width":442.24199999999996,"height":124.28000068664551}},{"text":"(Francisca)                                                                         (1981)","targetRectangle":{"y":426.28000068664551,"x":111.49000003496803,"width":565.71900000000051,"height":70.280000686645508}},{"text":"Vale Abraão                                                               (Abraham’s Valley)                              (1993)","targetRectangle":{"y":496.56000137329102,"x":111.49000003496803,"width":510.28469999999993,"height":97.280000686645508}},{"text":"O Convento                                                (The Convent)                                             (1995)","targetRectangle":{"y":593.84000205993652,"x":111.49000003496803,"width":430.96080000000029,"height":97.280000686645508}},{"text":"Portugal","targetRectangle":{"y":741,"x":726.96000000000004,"width":82.079999999999927,"height":23}}],"baseLayer":{"animations":[],"initialState":{"affineTransform":[1,0,0,1,0,0],"masksToBounds":false,"rotation":0,"scale":1,"position":{"pointX":512,"pointY":384},"width":1024,"sublayerTransform":[1,0,0,0,0,1,0,0,0,0,1,0,0,0,0,1],"contentsRect":{"y":0,"x":0,"width":1,"height":1},"opacity":1,"edgeAntialiasingMask":251658240,"height":768,"hidden":false,"anchorPoint":{"pointX":0.5,"pointY":0.5}},"objectID":"0","layers":[{"animations":[],"initialState":{"affineTransform":[1,0,0,1,0,0],"masksToBounds":false,"rotation":0,"scale":1,"position":{"pointX":512,"pointY":384},"width":1024,"sublayerTransform":[1,0,0,0,0,1,0,0,0,0,1,-0.00049229876906403734,0,0,0,1],"contentsRect":{"y":0,"x":0,"width":1,"height":1},"opacity":1,"edgeAntialiasingMask":251658240,"height":768,"hidden":false,"anchorPoint":{"pointX":0.5,"pointY":0.5}},"layers":[{"animations":[],"layers":[],"texturedRectangle":{"isBackgroundTexture":false,"singleTextureOpacity":1,"textureType":0,"textBaseline":0,"textXHeight":0,"isVerticalText":false},"initialState":{"affineTransform":[1,0,0,1,0,0],"masksToBounds":false,"rotation":0,"scale":1,"position":{"pointX":512,"pointY":384},"width":1024,"sublayerTransform":[1,0,0,0,0,1,0,0,0,0,1,0,0,0,0,1],"contentsRect":{"y":0,"x":0,"width":1,"height":1},"opacity":1,"edgeAntialiasingMask":0,"height":768,"hidden":false,"anchorPoint":{"pointX":0.5,"pointY":0.5}},"texture":"C725CB90B3A1E5FF17DB9DDA74434158"}]}]}}]}